py_api_saga/__init__.py
py_api_saga/py_api_saga.py
py_api_saga-0.0.3.dist-info/LICENSE
py_api_saga-0.0.3.dist-info/METADATA
py_api_saga-0.0.3.dist-info/WHEEL
py_api_saga-0.0.3.dist-info/top_level.txt
py_api_saga-0.0.3.dist-info/RECORD
