Metadata-Version: 2.1
Name: py-api-saga
Version: 0.0.3
Summary: UNKNOWN
Home-page: https://github.com/RupamSolanki/py_api_saga
Author: Rupam Solanki
Author-email: rupam.solanki1412@gmail.com
License: MIT
Keywords: saga,api_saga,resi_api,python,api,roll_back,transitions
Platform: UNKNOWN
Classifier: Programming Language :: Python :: 3
Classifier: License :: OSI Approved :: MIT License
Classifier: Operating System :: OS Independent
Requires-Python: >=3.6
License-File: LICENSE
